traa-0.1.5.data/purelib/traa/__init__.py
traa-0.1.5.data/purelib/traa/_traa_cffi.py
traa-0.1.5.data/purelib/traa/traa.py
traa-0.1.5.data/purelib/traa/libs/darwin/libtraa.dylib
traa-0.1.5.dist-info/LICENSE
traa-0.1.5.dist-info/METADATA
traa-0.1.5.dist-info/WHEEL
traa-0.1.5.dist-info/top_level.txt
traa-0.1.5.dist-info/RECORD
