Metadata-Version: 2.1
Name: traa
Version: 0.1.5
Summary: Python bindings for the TRAA (To Record Anything Anywhere) library - a high-performance, cross-platform solution for screen capture, window enumeration, and desktop recording. Supports Windows, macOS, and Linux with a clean, Pythonic API.
Home-page: https://github.com/opentraa/traa-py
Author: opentraa
Author-email: Sylar <peilinok@gmail.com>
License: BSD 3-Clause License
Project-URL: Homepage, https://github.com/opentraa/traa-py
Project-URL: Issues, https://github.com/opentraa/traa-py/issues
Keywords: Screen Capturer,Snapshot,Desktop Capturer
Platform: Windows
Platform: Linux
Platform: macOS
Classifier: Development Status :: 4 - Beta
Classifier: Intended Audience :: Developers
Classifier: License :: OSI Approved :: BSD License
Classifier: Operating System :: OS Independent
Classifier: Programming Language :: Python :: 3
Classifier: Programming Language :: Python :: 3.7
Classifier: Programming Language :: Python :: 3.8
Classifier: Programming Language :: Python :: 3.9
Classifier: Programming Language :: Python :: 3.10
Classifier: Programming Language :: Python :: 3.11
Classifier: Topic :: Software Development :: Libraries :: Python Modules
Requires-Python: >=3.7
License-File: LICENSE
Requires-Dist: cffi>=1.17.1
Requires-Dist: numpy>=2.2.3
Provides-Extra: dev
Requires-Dist: pytest>=6.0.0; extra == "dev"
Requires-Dist: pytest-cov>=2.0.0; extra == "dev"
Requires-Dist: black>=21.0.0; extra == "dev"
Requires-Dist: isort>=5.0.0; extra == "dev"
Requires-Dist: flake8>=3.9.0; extra == "dev"
Requires-Dist: wheel>=0.37.0; extra == "dev"
